hydra/__init__.py
python_hydra-1.3.1.dist-info/LICENSE
python_hydra-1.3.1.dist-info/METADATA
python_hydra-1.3.1.dist-info/WHEEL
python_hydra-1.3.1.dist-info/top_level.txt
python_hydra-1.3.1.dist-info/RECORD
